webpagetester/__init__.py
webpagetester/pagetester.py
webpagetester/scripts/__init__.py
webpagetester/scripts/link_comparator.py
webpagetester/scripts/webtester.py
webpagetester-0.1.5.dist-info/METADATA
webpagetester-0.1.5.dist-info/WHEEL
webpagetester-0.1.5.dist-info/entry_points.txt
webpagetester-0.1.5.dist-info/top_level.txt
webpagetester-0.1.5.dist-info/RECORD
