Metadata-Version: 2.1
Name: webpagetester
Version: 0.1.5
Summary: Basic Tool for automated testing if libraries exists
Home-page: https://github.com/willi-z/mdd
Author: WILLI Zschiebsch
License: BSD-3-Clause
Project-URL: Source Code, https://github.com/willi-z/msys
Project-URL: Issue Tracker, https://github.com/willi-z/msys/issues/
Platform: UNKNOWN
Requires-Python: >=3.7
Requires-Dist: setuptools (~=56.0.0)
Requires-Dist: requests (~=2.25.1)
Requires-Dist: urllib3 (~=1.26.3)
Requires-Dist: click (~=8.0)
